pyvortex/__init__.py
pyvortex/pyvortex.py
pyvortex-0.2.3.dist-info/LICENSE
pyvortex-0.2.3.dist-info/METADATA
pyvortex-0.2.3.dist-info/WHEEL
pyvortex-0.2.3.dist-info/top_level.txt
pyvortex-0.2.3.dist-info/RECORD
