Metadata-Version: 2.1
Name: pyvortex
Version: 0.2.3
Summary: Polar vortex edge detection using Nash criteria
Home-page: https://github.com/pankajkarman/pyvortex
Author: Pankaj Kumar
Author-email: pankaj.kmr1990@gmail.com
License: MIT
Platform: UNKNOWN
Requires-Python: >=3.6
Requires-Dist: numpy
Requires-Dist: pandas
Requires-Dist: xarray
Requires-Dist: matplotlib
